[
    {
        "origin": "chess-results",
        "nombre": "VII Open Internacional de Ajedrez Dama Negra",
        "ciudad": "C. Vicente Savall Pascual, 16, 03690 Sant Vicent del Raspeig, Alicante",
        "fechaini": "26-12-2026",
        "fechafin": "30-12-2026",
        "organizador": "Club de Ajedrez Dama Negra",
        "ritmo": "90 min + 30 sec per move from the first move",
        "lat": 38.3915493,
        "lon": -0.5208521,
        "link": "https://chess-results.com/tnr1418723.aspx?lan=2"
    },
    {
        "origin": "chess-results",
        "nombre": "Copa por Equipos Gran Hotel Bali 2026- Sub 12",
        "ciudad": "Hotel Bali - Benidorm (Alicante - SPAIN)",
        "fechaini": "05-12-2026",
        "fechafin": "08-12-2026",
        "organizador": "AO Barona Boj, Luis (22239030)",
        "ritmo": "60 minutos + 30 segundos por movimiento",
        "lat": 40.4167,
        "lon": -3.7033,
        "link": "https://chess-results.com/tnr1439481.aspx?lan=2"
    },
    {
        "origin": "chess-results",
        "nombre": "Copa por Equipos Gran Hotel Bali 2026- Sub 14",
        "ciudad": "Hotel Bali - Benidorm (Alicante - SPAIN)",
        "fechaini": "05-12-2026",
        "fechafin": "08-12-2026",
        "organizador": "AO Barona Boj, Luis (22239030)",
        "ritmo": "60 minutos + 30 segundos por movimiento",
        "lat": 40.4167,
        "lon": -3.7033,
        "link": "https://chess-results.com/tnr1439479.aspx?lan=2"
    },
    {
        "origin": "chess-results",
        "nombre": "Copa por Equipos Gran Hotel Bali 2026- Sub 16",
        "ciudad": "Hotel Bali - Benidorm (Alicante - SPAIN)",
        "fechaini": "05-12-2026",
        "fechafin": "08-12-2026",
        "organizador": "AO Barona Boj, Luis (22239030)",
        "ritmo": "60 minutos + 30 segundos por movimiento",
        "lat": 40.4167,
        "lon": -3.7033,
        "link": "https://chess-results.com/tnr1439478.aspx?lan=2"
    },
    {
        "origin": "chess-results",
        "nombre": "Copa por Equipos Gran Hotel Bali 2026- Sub 18",
        "ciudad": "Hotel Bali - Benidorm (Alicante - SPAIN)",
        "fechaini": "05-12-2026",
        "fechafin": "08-12-2026",
        "organizador": "AO Barona Boj, Luis (22239030)",
        "ritmo": "60 minutos + 30 segundos por movimiento",
        "lat": 40.4167,
        "lon": -3.7033,
        "link": "https://chess-results.com/tnr1439477.aspx?lan=2"
    },
    {
        "origin": "chess-results",
        "nombre": "I Copa Internacional por Equipos Gran Hotel Bali 2",
        "ciudad": "Hotel Bali - Benidorm (Alicante - SPAIN)",
        "fechaini": "05-12-2026",
        "fechafin": "08-12-2026",
        "organizador": "AO Barona Boj, Luis (22239030)",
        "ritmo": "60 minutos + 30 segundos por movimiento",
        "lat": 40.4167,
        "lon": -3.7033,
        "link": "https://chess-results.com/tnr1404738.aspx?lan=2"
    },
    {
        "origin": "chess-results",
        "nombre": "VII elllobregat Open Group B - Memorial Arturo Pom",
        "ciudad": "Sant Boi de Llobregat, Can Massallera, Carrer Mallorca 30 Sant Boi de Llobregat",
        "fechaini": "05-12-2026",
        "fechafin": "06-12-2026",
        "organizador": "OA Perez Llorca, Xavier 24583880",
        "ritmo": "15 min + 5 sec from move 1",
        "lat": 40.4167,
        "lon": -3.7033,
        "link": "https://chess-results.com/tnr1429493.aspx?lan=2"
    },
    {
        "origin": "chess-results",
        "nombre": "VII elllobregat Open Group A",
        "ciudad": "Sant Boi de Llobregat",
        "fechaini": "03-12-2026",
        "fechafin": "08-12-2026",
        "organizador": "OA Perez Llorca, Xavier 24583880",
        "ritmo": "90min + 30sec from move 1",
        "lat": 41.3241016,
        "lon": 2.0511278,
        "link": "https://chess-results.com/tnr1429492.aspx?lan=2"
    },
    {
        "origin": "chess-results",
        "nombre": "XVII Torneo Blitz Nocturno Gran Hotel Bali 2026-Gr",
        "ciudad": "Hotel Bali - Benidorm (Alicante - SPAIN)",
        "fechaini": "02-12-2026",
        "fechafin": "03-12-2026",
        "organizador": "AO Barona Boj, Luis (22239030)",
        "ritmo": "3 minutes with 2 second increment from move 1",
        "lat": 40.4167,
        "lon": -3.7033,
        "link": "https://chess-results.com/tnr1404736.aspx?lan=2"
    },
    {
        "origin": "chess-results",
        "nombre": "XVII Torneo Blitz Nocturno Gran Hotel Bali 2026-Gr",
        "ciudad": "Hotel Bali - Benidorm (Alicante - SPAIN)",
        "fechaini": "02-12-2026",
        "fechafin": "03-12-2026",
        "organizador": "AO Barona Boj, Luis (22239030)",
        "ritmo": "3 minutes with 2 second increment from move 1",
        "lat": 40.4167,
        "lon": -3.7033,
        "link": "https://chess-results.com/tnr1404737.aspx?lan=2"
    },
    {
        "origin": "chess-results",
        "nombre": "31 San Andres - Azkoitia 2026",
        "ciudad": "",
        "fechaini": "28-11-2026",
        "fechafin": "28-11-2026",
        "organizador": "Anaitasuna-Kakute Xake Taldea",
        "ritmo": "Blitz, 3 minutos + 2 segundos por jugada.",
        "lat": 39.3260685,
        "lon": -4.8379791,
        "link": "https://chess-results.com/tnr1356330.aspx?lan=2"
    },
    {
        "origin": "chess-results",
        "nombre": "XXIII Open Internacional Gran Hotel Bali 2026",
        "ciudad": "Gran Hotel Bali (Benidorm), Salón Terraza de Cristal, floor/planta +1",
        "fechaini": "28-11-2026",
        "fechafin": "05-12-2026",
        "organizador": "Club Deportivo Tossal de la Cala",
        "ritmo": "Standard: 90 minutes with 30 second increment from move 1",
        "lat": 40.4167,
        "lon": -3.7033,
        "link": "https://chess-results.com/tnr1411135.aspx?lan=2"
    },
    {
        "origin": "chess-results",
        "nombre": "XXIII Torneo Internacional Gran Hotel Bali Grupo B",
        "ciudad": "Hotel Bali - Benidorm (Alicante - SPAIN)",
        "fechaini": "28-11-2026",
        "fechafin": "05-12-2026",
        "organizador": "Club Deportivo Tossal de la Cala",
        "ritmo": "Standard: 90 minutes with 30 second increment from move 1",
        "lat": 40.4167,
        "lon": -3.7033,
        "link": "https://chess-results.com/tnr1404735.aspx?lan=2"
    },
    {
        "origin": "chess-results",
        "nombre": "IV INTERNACIONAL CHESS OPEN HOTEL CAP NEGRET 50May",
        "ciudad": "Altea (Spain)",
        "fechaini": "07-11-2026",
        "fechafin": "14-11-2026",
        "organizador": "Asociación de Ajedrez Social y Terapéutico de la C.V. colabora  H Cap Negret",
        "ritmo": "90 min + 30 seg. for mov",
        "lat": 40.4167,
        "lon": -3.7033,
        "link": "https://chess-results.com/tnr1383657.aspx?lan=2"
    },
    {
        "origin": "chess-results",
        "nombre": "IV INTERNACIONAL CHESS OPEN HOTEL CAP NEGRET 65May",
        "ciudad": "Altea (Spain)",
        "fechaini": "07-11-2026",
        "fechafin": "14-11-2026",
        "organizador": "Asociación de Ajedrez Social y Terapéutico de la C.V. colabora  H Cap Negret",
        "ritmo": "90 min + 30 seg. for mov",
        "lat": 40.4167,
        "lon": -3.7033,
        "link": "https://chess-results.com/tnr1383655.aspx?lan=2"
    },
    {
        "origin": "chess-results",
        "nombre": "2º Open Internacional Sub2200 \"Hotel Vértice CHIPI",
        "ciudad": "HOTEL VERTICE CHIPIONA MAR ***, Paseo Costa de la Luz N55, Av. De Sevilla, Nº58",
        "fechaini": "06-11-2026",
        "fechafin": "08-11-2026",
        "organizador": "Vértice Hoteles - Asociación de Amigos por el Desarrollo del Ajedrez",
        "ritmo": "80 minutos + 10 segundos por jugador",
        "lat": 40.4167,
        "lon": -3.7033,
        "link": "https://chess-results.com/tnr1346686.aspx?lan=2"
    },
    {
        "origin": "chess-results",
        "nombre": "II Torneo Activo Lanzaloe-OneChess 2026 (Campeonat",
        "ciudad": "Sociedad Democracia, Avda. Rafael González, 19. Arrecife (Lanzarote)",
        "fechaini": "24-10-2026",
        "fechafin": "25-10-2026",
        "organizador": "Lanzaloe OneChess / Federación Canaria de Ajedrez",
        "ritmo": "10 min + 5 seg por movimiento",
        "lat": 40.4167,
        "lon": -3.7033,
        "link": "https://chess-results.com/tnr1409584.aspx?lan=2"
    },
    {
        "origin": "chess-results",
        "nombre": "I Blitz Lanzaloe-OneChess 2026",
        "ciudad": "Sociedad Democracia, Avda. Rafael González, 19. Arrecife (Lanzarote)",
        "fechaini": "23-10-2026",
        "fechafin": "23-10-2026",
        "organizador": "Lanzaloe OneChess / Federación Canaria de Ajedrez",
        "ritmo": "3 min + 2 seg por movimiento",
        "lat": 40.4167,
        "lon": -3.7033,
        "link": "https://chess-results.com/tnr1409583.aspx?lan=2"
    },
    {
        "origin": "chess-results",
        "nombre": "XXIII Calvia Amateur Open",
        "ciudad": "Calvià (Mallorca)",
        "fechaini": "10-10-2026",
        "fechafin": "18-10-2026",
        "organizador": "Sergio Estremera Paños",
        "ritmo": "90mn 40 jugadas + 15min + 30seg desde la jugada 1",
        "lat": 39.5021057,
        "lon": 2.5332835,
        "link": "https://chess-results.com/tnr1332965.aspx?lan=2"
    },
    {
        "origin": "chess-results",
        "nombre": "3er Social Otoño 2026 CA Monteolivete",
        "ciudad": "CA Monteolivete",
        "fechaini": "05-10-2026",
        "fechafin": "14-12-2026",
        "organizador": "",
        "ritmo": "30+30",
        "lat": 39.4593043,
        "lon": -0.3638668,
        "link": "https://chess-results.com/tnr1438104.aspx?lan=2"
    },
    {
        "origin": "chess-results",
        "nombre": "Trofeo Sant Antoni de Portmany - Amateur",
        "ciudad": "Sant Antoni de Portmany(Ibiza)",
        "fechaini": "04-10-2026",
        "fechafin": "04-10-2026",
        "organizador": "Nicolo Napoli",
        "ritmo": "10 minutes + 5 seconds per move",
        "lat": 38.9830568,
        "lon": 1.3009485,
        "link": "https://chess-results.com/tnr1398535.aspx?lan=2"
    },
    {
        "origin": "chess-results",
        "nombre": "RAPID FIDE - Ibiza Travel 2026",
        "ciudad": "Sant Antoni de Portmany(Ibiza)",
        "fechaini": "03-10-2026",
        "fechafin": "03-10-2026",
        "organizador": "Napoli, Nicolo (813702)",
        "ritmo": "10 minutes + 5 seconds per move",
        "lat": 38.9830568,
        "lon": 1.3009485,
        "link": "https://chess-results.com/tnr1385073.aspx?lan=2"
    },
    {
        "origin": "chess-results",
        "nombre": "BLITZ FIDE - Ibiza Travel 2026",
        "ciudad": "Sant Antoni de Portmany(Ibiza)",
        "fechaini": "02-10-2026",
        "fechafin": "02-10-2026",
        "organizador": "Napoli, Nicolo (813702)",
        "ritmo": "3 minutes + 2 seconds per move",
        "lat": 38.9830568,
        "lon": 1.3009485,
        "link": "https://chess-results.com/tnr1385074.aspx?lan=2"
    },
    {
        "origin": "chess-results",
        "nombre": "VI Torneo Activo Dragones-Playitas 2026-Circuito C",
        "ciudad": "Playitas Resort, Tuineje (Fuerteventura)",
        "fechaini": "26-09-2026",
        "fechafin": "27-09-2026",
        "organizador": "Cabildo de Fuerteventura / CA Dragones de Fuerteventura",
        "ritmo": "10 minutos + 5 segundos por movimiento",
        "lat": 40.4167,
        "lon": -3.7033,
        "link": "https://chess-results.com/tnr1399686.aspx?lan=2"
    },
    {
        "origin": "chess-results",
        "nombre": "VI Torneo Blitz Nocturno Dragones-Playitas 2026-IV",
        "ciudad": "Playitas Resort, Tuineje (Fuerteventura)",
        "fechaini": "25-09-2026",
        "fechafin": "25-09-2026",
        "organizador": "CD de Ajedrez Henar y sus Dragones",
        "ritmo": "3 minutos + 2 segundos de incremento por jugador",
        "lat": 40.4167,
        "lon": -3.7033,
        "link": "https://chess-results.com/tnr1399685.aspx?lan=2"
    },
    {
        "origin": "chess-results",
        "nombre": "II OPEN DE TORRELODONES Memorial Ramón Torres Torn",
        "ciudad": "Torrelodones, Madrid",
        "fechaini": "20-09-2026",
        "fechafin": "20-09-2026",
        "organizador": "Club de Ajedrez Torrelodones",
        "ritmo": "10 minutes + 3 seconds per movement",
        "lat": 40.5762809,
        "lon": -3.928603,
        "link": "https://chess-results.com/tnr1429140.aspx?lan=2"
    },
    {
        "origin": "chess-results",
        "nombre": "II OPEN DE TORRELODONES Memorial Ramón Torres Grup",
        "ciudad": "Torrelodones, Madrid",
        "fechaini": "18-09-2026",
        "fechafin": "26-09-2026",
        "organizador": "Club de Ajedrez Torrelodones",
        "ritmo": "90 minutes + 30 seconds per movement",
        "lat": 40.5762809,
        "lon": -3.928603,
        "link": "https://chess-results.com/tnr1417768.aspx?lan=2"
    },
    {
        "origin": "chess-results",
        "nombre": "II OPEN DE TORRELODONES Memorial Ramón Torres Grup",
        "ciudad": "Torrelodones, Madrid",
        "fechaini": "18-09-2026",
        "fechafin": "26-09-2026",
        "organizador": "Club de Ajedrez Torrelodones",
        "ritmo": "90 minutes + 30 seconds per movement",
        "lat": 40.5762809,
        "lon": -3.928603,
        "link": "https://chess-results.com/tnr1429138.aspx?lan=2"
    },
    {
        "origin": "chess-results",
        "nombre": "Marias xake Grupo 1",
        "ciudad": "",
        "fechaini": "17-09-2026",
        "fechafin": "10-06-2027",
        "organizador": "",
        "ritmo": "30+0",
        "lat": 39.3260685,
        "lon": -4.8379791,
        "link": "https://chess-results.com/tnr1442290.aspx?lan=2"
    },
    {
        "origin": "chess-results",
        "nombre": "Marias xake Grupo 2",
        "ciudad": "",
        "fechaini": "17-09-2026",
        "fechafin": "10-06-2027",
        "organizador": "",
        "ritmo": "",
        "lat": 39.3260685,
        "lon": -4.8379791,
        "link": "https://chess-results.com/tnr1442366.aspx?lan=2"
    },
    {
        "origin": "chess-results",
        "nombre": "XVII Memorial Santiago Tejero",
        "ciudad": "Agrupacion artistica aragonesa (C/ Lagasca nº23,Zaragoza, España)",
        "fechaini": "13-09-2026",
        "fechafin": "13-09-2026",
        "organizador": "",
        "ritmo": "12'+3''",
        "lat": 40.4167,
        "lon": -3.7033,
        "link": "https://chess-results.com/tnr1411031.aspx?lan=2"
    },
    {
        "origin": "chess-results",
        "nombre": "41º. Open Ezkerraldea Basque Country - 34º Magistr",
        "ciudad": "",
        "fechaini": "08-09-2026",
        "fechafin": "13-09-2026",
        "organizador": "Sestao Xake Taldea",
        "ritmo": "90min+30 sg/mov",
        "lat": 39.3260685,
        "lon": -4.8379791,
        "link": "https://chess-results.com/tnr1335005.aspx?lan=2"
    },
    {
        "origin": "chess-results",
        "nombre": "41º. Open Ezkerraldea Basque Country - Sub 2000",
        "ciudad": "",
        "fechaini": "08-09-2026",
        "fechafin": "13-09-2026",
        "organizador": "Sestao Xake Taldea",
        "ritmo": "90min+30 sg/mov",
        "lat": 39.3260685,
        "lon": -4.8379791,
        "link": "https://chess-results.com/tnr1397639.aspx?lan=2"
    },
    {
        "origin": "chess-results",
        "nombre": "IV ACTIVO INTERNACIONAL FRANCISCO PULIDO PACO PULI",
        "ciudad": "Vega de San Mateo",
        "fechaini": "07-09-2026",
        "fechafin": "07-09-2026",
        "organizador": "Club de Ajedrez San Mateo",
        "ritmo": "10 min + 5 seg/mov",
        "lat": 27.9961882,
        "lon": -15.5682128,
        "link": "https://chess-results.com/tnr1419749.aspx?lan=2"
    },
    {
        "origin": "chess-results",
        "nombre": "I NOCTURNO VEGA DE SAN MATEO",
        "ciudad": "Vega de San Mateo",
        "fechaini": "06-09-2026",
        "fechafin": "06-09-2026",
        "organizador": "Club de Ajedrez San Mateo",
        "ritmo": "5min + 3 seg/mov",
        "lat": 27.9961882,
        "lon": -15.5682128,
        "link": "https://chess-results.com/tnr1419750.aspx?lan=2"
    },
    {
        "origin": "chess-results",
        "nombre": "I Cerrado Internacional GM MyInvestor",
        "ciudad": "Zaragoza",
        "fechaini": "05-09-2026",
        "fechafin": "12-09-2026",
        "organizador": "MyInvestor - Stadium Casablanca",
        "ritmo": "90 min. + 30 seg.  mov.",
        "lat": 41.6915847,
        "lon": -0.9101268,
        "link": "https://chess-results.com/tnr1441616.aspx?lan=2"
    },
    {
        "origin": "chess-results",
        "nombre": "I Cerrado Internacional MI MyInvestor",
        "ciudad": "Zaragoza",
        "fechaini": "05-09-2026",
        "fechafin": "12-09-2026",
        "organizador": "MyInvestor - Stadium Casablanca",
        "ritmo": "90 min. + 30 seg.  mov.",
        "lat": 41.6915847,
        "lon": -0.9101268,
        "link": "https://chess-results.com/tnr1441618.aspx?lan=2"
    },
    {
        "origin": "chess-results",
        "nombre": "I Open Internacional MyInvestor Casablanca",
        "ciudad": "",
        "fechaini": "05-09-2026",
        "fechafin": "12-09-2026",
        "organizador": "MyInvestor - Stadium Casablanca",
        "ritmo": "90 min. + 30 seg.  mov.",
        "lat": 39.3260685,
        "lon": -4.8379791,
        "link": "https://chess-results.com/tnr1441613.aspx?lan=2"
    },
    {
        "origin": "chess-results",
        "nombre": "X Torneo Ajedrez Ciudad de Guadix. “Memorial Luis",
        "ciudad": "Biblioteca Municipal, Plaza San Francisco 4, GUADIX (GRANADA)",
        "fechaini": "05-09-2026",
        "fechafin": "05-09-2026",
        "organizador": "Club Ajedrez Ciudad de Guadix",
        "ritmo": "8+3",
        "lat": 40.4167,
        "lon": -3.7033,
        "link": "https://chess-results.com/tnr1376314.aspx?lan=2"
    },
    {
        "origin": "chess-results",
        "nombre": "XXXI Open Internacional Virgen de ValenciaVioño de",
        "ciudad": "Viono de Pielagos",
        "fechaini": "04-09-2026",
        "fechafin": "07-09-2026",
        "organizador": "M.A. Muela Perez (I.O. 22260102)",
        "ritmo": "90 min + 30 seg",
        "lat": 43.3613846,
        "lon": -3.9707742,
        "link": "https://chess-results.com/tnr1444147.aspx?lan=2"
    },
    {
        "origin": "chess-results",
        "nombre": "II Torneo de Verano en Fresnedillas",
        "ciudad": "Casa de la CUltura, fresnedillas de la Oliva",
        "fechaini": "01-09-2026",
        "fechafin": "18-09-2026",
        "organizador": "Club Ajedrez de Fresnedillas",
        "ritmo": "60'+30'' from 1st",
        "lat": 40.4167,
        "lon": -3.7033,
        "link": "https://chess-results.com/tnr1428662.aspx?lan=2"
    },
    {
        "origin": "chess-results",
        "nombre": "III Torneig Social Penya Alfil 2026",
        "ciudad": "",
        "fechaini": "01-09-2026",
        "fechafin": "13-10-2026",
        "organizador": "Penya Alfil des Mercadal",
        "ritmo": "60 minuts per partida amb un increment de 15 segons a partir de la primera jugada.",
        "lat": 39.3260685,
        "lon": -4.8379791,
        "link": "https://chess-results.com/tnr1354301.aspx?lan=2"
    },
    {
        "origin": "chess-results",
        "nombre": "IV TORNEO INTERNACIONAL VEGA DE SAN MATEO",
        "ciudad": "Vega de San Mateo",
        "fechaini": "31-08-2026",
        "fechafin": "06-09-2026",
        "organizador": "Club de Ajedrez San Mateo",
        "ritmo": "90 MIN + 30 SEG/MOV",
        "lat": 27.9961882,
        "lon": -15.5682128,
        "link": "https://chess-results.com/tnr1419747.aspx?lan=2"
    },
    {
        "origin": "chess-results",
        "nombre": "XXXVII Vila de Xàbia 2026XXXIV Mare de Déu de Lore",
        "ciudad": "C/ Severo Ochoa, Xàbia / Javea (Alicante)",
        "fechaini": "30-08-2026",
        "fechafin": "30-08-2026",
        "organizador": "C.A. Xàbia y comisión fiestas Mare de Déu del Loreto",
        "ritmo": "5'+3'' incremento por jugada",
        "lat": 38.7936667,
        "lon": 0.1804966,
        "link": "https://chess-results.com/tnr1327068.aspx?lan=2"
    },
    {
        "origin": "chess-results",
        "nombre": "II Memorial Emilio Sánchez Jerez (+8.000€ EN PREMI",
        "ciudad": "Rincón Huertano (Beniaján, Murcia)",
        "fechaini": "29-08-2026",
        "fechafin": "29-08-2026",
        "organizador": "CAC Beniaján",
        "ritmo": "10 min + 5 seg incremento desde jugada 1",
        "lat": 40.4167,
        "lon": -3.7033,
        "link": "https://chess-results.com/tnr1387431.aspx?lan=2"
    },
    {
        "origin": "chess-results",
        "nombre": "III ACTIVO INTERNACIONAL DE AJEDREZ SAN CRISTOBAL",
        "ciudad": "SAN CRISTOBAL DE LA LAGUNA",
        "fechaini": "29-08-2026",
        "fechafin": "30-08-2026",
        "organizador": "ORGANISMO AUTONOMO DEPORTES - FEDERACION CANARIA AJEDREZ",
        "ritmo": "15 MIN + 5 SEC/MOVE FROM 1",
        "lat": 28.4857715,
        "lon": -16.3159422,
        "link": "https://chess-results.com/tnr1444123.aspx?lan=2"
    },
    {
        "origin": "chess-results",
        "nombre": "I Open Sub 1700 FIDE El Colorado",
        "ciudad": "Salón Multiusos El Colorado (Salón Climatizado) - Conil de la Frontera (Cádiz)",
        "fechaini": "28-08-2026",
        "fechafin": "30-08-2026",
        "organizador": "Club de Ajedrez Conil",
        "ritmo": "80+10",
        "lat": 40.4167,
        "lon": -3.7033,
        "link": "https://chess-results.com/tnr1422835.aspx?lan=2"
    },
    {
        "origin": "chess-results",
        "nombre": "I Open Sub 2200 FIDE El Colorado",
        "ciudad": "Salón Multiusos El Colorado (Salón Climatizado) - Conil de la Frontera (Cádiz)",
        "fechaini": "28-08-2026",
        "fechafin": "30-08-2026",
        "organizador": "Club de Ajedrez Conil",
        "ritmo": "80+10",
        "lat": 40.4167,
        "lon": -3.7033,
        "link": "https://chess-results.com/tnr1422827.aspx?lan=2"
    },
    {
        "origin": "chess-results",
        "nombre": "XII Torneo de Ajedrez de Tardienta 2026",
        "ciudad": "Tardienta",
        "fechaini": "23-08-2026",
        "fechafin": "23-08-2026",
        "organizador": "Ayuntamiento de Tardienta",
        "ritmo": "5 min +3 seg/jug",
        "lat": 41.9784326,
        "lon": -0.536013,
        "link": "https://chess-results.com/tnr1439432.aspx?lan=2"
    },
    {
        "origin": "chess-results",
        "nombre": "FESTIVAL - TORNEO C 2º Nocturno Trebejo Solidario",
        "ciudad": "HOTEL VERTICE SEVILLA ALJARAFE ****, Avenida República Argentina s/n, Bormujos",
        "fechaini": "22-08-2026",
        "fechafin": "22-08-2026",
        "organizador": "Asociación de Amigos por el Desarrollo del Ajedrez",
        "ritmo": "3 minutos + 2 segundos por jugador",
        "lat": 40.4167,
        "lon": -3.7033,
        "link": "https://chess-results.com/tnr1346666.aspx?lan=2"
    },
    {
        "origin": "chess-results",
        "nombre": "Torneo Ajedrez San Agustín Cúllar 2026",
        "ciudad": "SENPA, Pabellón Deportivo y Cultural, 18850 Cúllar, Granada",
        "fechaini": "22-08-2026",
        "fechafin": "22-08-2026",
        "organizador": "Excmo.Ayuntamiento de Cúllar",
        "ritmo": "8min+5seg/jugada",
        "lat": 40.4167,
        "lon": -3.7033,
        "link": "https://chess-results.com/tnr1392956.aspx?lan=2"
    },
    {
        "origin": "chess-results",
        "nombre": "VII TORNEO INTERNACIONAL DE AJEDREZ SAN CRISTOBAL",
        "ciudad": "SAN CRISTOBAL DE LA LAGUNA",
        "fechaini": "22-08-2026",
        "fechafin": "29-08-2026",
        "organizador": "ORGANISMO AUTONOMO DEPORTES - FEDERACION CANARIA AJEDREZ",
        "ritmo": "90 MIN + 30 SEC/MOVE FROM 1",
        "lat": 28.4857715,
        "lon": -16.3159422,
        "link": "https://chess-results.com/tnr1405186.aspx?lan=2"
    },
    {
        "origin": "chess-results",
        "nombre": "FESTIVAL - TORNEO A 8º Open Sub2200 \"Hotel Vértice",
        "ciudad": "HOTEL VERTICE SEVILLA ALJARAFE ****, Avenida República Argentina s/n, Bormujos",
        "fechaini": "21-08-2026",
        "fechafin": "23-08-2026",
        "organizador": "Asociación de Amigos por el Desarrollo del Ajedrez",
        "ritmo": "80 minutos + 10 segundos por jugador",
        "lat": 40.4167,
        "lon": -3.7033,
        "link": "https://chess-results.com/tnr1346658.aspx?lan=2"
    },
    {
        "origin": "chess-results",
        "nombre": "FESTIVAL - TORNEO B 5º Open Sub1800 \"Hotel Vértice",
        "ciudad": "HOTEL VERTICE SEVILLA ALJARAFE ****, Avenida República Argentina s/n, Bormujos",
        "fechaini": "21-08-2026",
        "fechafin": "23-08-2026",
        "organizador": "Asociación de Amigos por el Desarrollo del Ajedrez",
        "ritmo": "80 minutos + 10 segundos por jugador",
        "lat": 40.4167,
        "lon": -3.7033,
        "link": "https://chess-results.com/tnr1346660.aspx?lan=2"
    },
    {
        "origin": "chess-results",
        "nombre": "VI BLITZ INTERNACIONAL DE AJEDREZ SAN CRISTOBAL DE",
        "ciudad": "SAN CRISTOBAL DE LA LAGUNA",
        "fechaini": "21-08-2026",
        "fechafin": "21-08-2026",
        "organizador": "ORGANISMO AUTONOMO DEPORTES - FEDERACION CANARIA AJEDREZ",
        "ritmo": "3 MIN + 2 SEC/MOVE FROM 1",
        "lat": 28.4857715,
        "lon": -16.3159422,
        "link": "https://chess-results.com/tnr1444128.aspx?lan=2"
    },
    {
        "origin": "chess-results",
        "nombre": "II Torneo de Ajedrez de Verano de Arenas de San Pe",
        "ciudad": "",
        "fechaini": "16-08-2026",
        "fechafin": "16-08-2026",
        "organizador": "Ayuntamiento de Arenas de San Pedro",
        "ritmo": "10 minutos+ 3 segundos",
        "lat": 39.3260685,
        "lon": -4.8379791,
        "link": "https://chess-results.com/tnr1399394.aspx?lan=2"
    },
    {
        "origin": "chess-results",
        "nombre": "II Torneo de Ajedrez de Verano de Arenas de San Pe",
        "ciudad": "Polideportivo Jesús Navarro ( Arenas de San Pedro)",
        "fechaini": "16-08-2026",
        "fechafin": "16-08-2026",
        "organizador": "Ayuntamiento de Arenas de San Pedro",
        "ritmo": "10 minutos+ 3 segundos",
        "lat": 40.4167,
        "lon": -3.7033,
        "link": "https://chess-results.com/tnr1424937.aspx?lan=2"
    },
    {
        "origin": "chess-results",
        "nombre": "XLI Torneo Ajedrez Villa de Galera",
        "ciudad": "Solón Hotel Galera, GALERA (Granada)",
        "fechaini": "16-08-2026",
        "fechafin": "16-08-2026",
        "organizador": "Excmo.Ayuntamiento de Galera",
        "ritmo": "10+5",
        "lat": 40.4167,
        "lon": -3.7033,
        "link": "https://chess-results.com/tnr1395803.aspx?lan=2"
    },
    {
        "origin": "chess-results",
        "nombre": "COLONIAS DE VERANO 2026",
        "ciudad": "Zaragoza",
        "fechaini": "14-08-2026",
        "fechafin": "14-08-2026",
        "organizador": "Palacio de Pioneros",
        "ritmo": "15+3",
        "lat": 41.6915847,
        "lon": -0.9101268,
        "link": "https://chess-results.com/tnr1428328.aspx?lan=2"
    },
    {
        "origin": "chess-results",
        "nombre": "Torneo de Ajedrez Blitz Pub Fegatello",
        "ciudad": "Mondariz Balneario",
        "fechaini": "14-08-2026",
        "fechafin": "14-08-2026",
        "organizador": "Marcote Nunez, Jesus Javier",
        "ritmo": "3 minutes + 2 seconds",
        "lat": 42.2194134,
        "lon": -8.4713577,
        "link": "https://chess-results.com/tnr1393646.aspx?lan=2"
    },
    {
        "origin": "chess-results",
        "nombre": "XII Abierto Internacional de Ajedrez Hotel CEMAR",
        "ciudad": "Mondariz Balneario",
        "fechaini": "09-08-2026",
        "fechafin": "16-08-2026",
        "organizador": "Marcote Nunez, Jesus Javier",
        "ritmo": "90 minutes + 30 seconds",
        "lat": 42.2194134,
        "lon": -8.4713577,
        "link": "https://chess-results.com/tnr1388219.aspx?lan=2"
    },
    {
        "origin": "chess-results",
        "nombre": "IXTORNEO INTERNACIONAL DE AJEDREZ ISLA DE LA PALMA",
        "ciudad": "Pabellon Deportivo Roberto Estrello , Santa Cruz de La Palma (Canarias)",
        "fechaini": "07-08-2026",
        "fechafin": "14-08-2026",
        "organizador": "Centro Insular de Ajedrez de la Palma / Federacion Canaria de Ajedrez",
        "ritmo": "90 minutos + 30 segundos por movimiento",
        "lat": 40.4167,
        "lon": -3.7033,
        "link": "https://chess-results.com/tnr1359931.aspx?lan=2"
    },
    {
        "origin": "chess-results",
        "nombre": "VIII MEMORIAL FRANCISCO JOSE RODRIGUEZ CAMACHO \"KI",
        "ciudad": "PRIMERA PISTA PLAYA CALLE ASUNCION CON AV DE LA BARROSA",
        "fechaini": "05-08-2026",
        "fechafin": "05-08-2026",
        "organizador": "CDA RUY LOPEZ CHICLANA",
        "ritmo": "8 min + 3 seg por jugada",
        "lat": 40.4167,
        "lon": -3.7033,
        "link": "https://chess-results.com/tnr1434786.aspx?lan=2"
    },
    {
        "origin": "chess-results",
        "nombre": "I Torneig d'Escacs Festes de Gata 2026",
        "ciudad": "Ajuntament de Gata de Gorgos ( Sala CSI ) Gata de Gorgos  (03740), Alicante",
        "fechaini": "02-08-2026",
        "fechafin": "02-08-2026",
        "organizador": "Comissió de Festes de Gata de Gorgos",
        "ritmo": "5 minuts+3 segons d'increment per jugada",
        "lat": 40.4167,
        "lon": -3.7033,
        "link": "https://chess-results.com/tnr1402577.aspx?lan=2"
    },
    {
        "origin": "chess-results",
        "nombre": "XI Open Internacional de Ajedrez 64 Villalba",
        "ciudad": "Salon El Capricho Plaza los Cuatro Caños 28400 Collado Villalba (Madrid)",
        "fechaini": "01-08-2026",
        "fechafin": "09-08-2026",
        "organizador": "(IO) Luis Blasco de la Cruz (2219107)",
        "ritmo": "90 Min + 30 sec x Move from move 1.",
        "lat": 40.4167,
        "lon": -3.7033,
        "link": "https://chess-results.com/tnr1387689.aspx?lan=2"
    },
    {
        "origin": "chess-results",
        "nombre": "XXIV Torneo Internacional \"VILLA de BRENES\" 2026",
        "ciudad": "SALA BLAS INFANTE / Calle Amparo Mateo Silva s/n, 41310 Brenes - Sevilla.",
        "fechaini": "01-08-2026",
        "fechafin": "01-08-2026",
        "organizador": "Excmo. Ayuntamiento de Brenes",
        "ritmo": "8 min. + 3 seg. por jugada",
        "lat": 40.4167,
        "lon": -3.7033,
        "link": "https://chess-results.com/tnr1431764.aspx?lan=2"
    },
    {
        "origin": "chess-results",
        "nombre": "XXXVI Torneo Ajedrez GOR San Cayetano. Memorial Gr",
        "ciudad": "Centro Multiusos, Calle Ancha s/n, GOR, GRANADA",
        "fechaini": "01-08-2026",
        "fechafin": "01-08-2026",
        "organizador": "Excmo.Ayuntamiento de Gor",
        "ritmo": "8+3",
        "lat": 40.4167,
        "lon": -3.7033,
        "link": "https://chess-results.com/tnr1439736.aspx?lan=2"
    },
    {
        "origin": "chess-results",
        "nombre": "XLVIII OPEN DE CHIPIONA DE AJEDREZ SUB 2250 FADA",
        "ciudad": "Palacio de Exposiciones y Congresos (Avenida de Granada, 35",
        "fechaini": "31-07-2026",
        "fechafin": "02-08-2026",
        "organizador": "CLUB AJEDREZ CHIPIONA",
        "ritmo": "40 minutos + 10 segundos",
        "lat": 40.4167,
        "lon": -3.7033,
        "link": "https://chess-results.com/tnr1441626.aspx?lan=2"
    },
    {
        "origin": "chess-results",
        "nombre": "GAY GAMES 2026 RAPID",
        "ciudad": "La petxina, Valencia",
        "fechaini": "30-07-2026",
        "fechafin": "31-07-2026",
        "organizador": "C.D. BASILIO",
        "ritmo": "15 min + 3seg",
        "lat": 39.4735852,
        "lon": -0.3909546,
        "link": "https://chess-results.com/tnr1443123.aspx?lan=2"
    },
    {
        "origin": "chess-results",
        "nombre": "VI Torneo Internacional FIA 2026",
        "ciudad": "Hotel Fariones, C/Roque del Este, 1-Pto. del Carmen-Tías (Lanzarote)",
        "fechaini": "29-07-2026",
        "fechafin": "06-08-2026",
        "organizador": "Cial de Lanzarote / Escobar Lopez, Maria Cristina (ID 54541522)",
        "ritmo": "90 minutos + 30 segundos por movimiento",
        "lat": 40.4167,
        "lon": -3.7033,
        "link": "https://chess-results.com/tnr1317968.aspx?lan=2"
    },
    {
        "origin": "chess-results",
        "nombre": "⏰♟️ Granada Chess Open 2026",
        "ciudad": "Hotel Porcel Alixares, Granada",
        "fechaini": "28-07-2026",
        "fechafin": "02-08-2026",
        "organizador": "Club de Ajedrez Villa de La Zubia",
        "ritmo": "90'+30\"",
        "lat": 37.1725602,
        "lon": -3.5832041,
        "link": "https://chess-results.com/tnr1323252.aspx?lan=2"
    },
    {
        "origin": "chess-results",
        "nombre": "XIII Torneo Verano Alicante",
        "ciudad": "Real Liceo Casino de Alicante. Paseo de la Explanada de España Nº16",
        "fechaini": "27-07-2026",
        "fechafin": "02-08-2026",
        "organizador": "Club de Ajedrez Dama Negra",
        "ritmo": "90 minutes with 30 second increment from move 1",
        "lat": 40.4167,
        "lon": -3.7033,
        "link": "https://chess-results.com/tnr1376668.aspx?lan=2"
    },
    {
        "origin": "chess-results",
        "nombre": "II Open Internacional Ciudad de Vitoria - Gasteiz",
        "ciudad": "",
        "fechaini": "27-07-2026",
        "fechafin": "02-08-2026",
        "organizador": "",
        "ritmo": "90 min + 30 seg/mov",
        "lat": 39.3260685,
        "lon": -4.8379791,
        "link": "https://chess-results.com/tnr1348675.aspx?lan=2"
    },
    {
        "origin": "chess-results",
        "nombre": "XII O‏PEN FUNDACION VALENCIA CUNA",
        "ciudad": "VALENCIA, ESPAÑA",
        "fechaini": "27-07-2026",
        "fechafin": "02-08-2026",
        "organizador": "",
        "ritmo": "90 min + 30 segundos",
        "lat": 37.1665094,
        "lon": -4.1500582,
        "link": "https://chess-results.com/tnr1443112.aspx?lan=2"
    },
    {
        "origin": "chess-results",
        "nombre": "V Abierto de Ajedrez \"PEDRERA\" (Sevilla) - Domingo",
        "ciudad": "Caseta Municipal Pedrera, 41566 Pedrera - Sevilla",
        "fechaini": "26-07-2026",
        "fechafin": "26-07-2026",
        "organizador": "Excmo. Ayuntamiento de Pedrera y Club Fianchetto Sierra Sur",
        "ritmo": "8 min. + 3 seg.",
        "lat": 40.4167,
        "lon": -3.7033,
        "link": "https://chess-results.com/tnr1433215.aspx?lan=2"
    },
    {
        "origin": "chess-results",
        "nombre": "XXX Social Blitz Anaitasuna-Kakute Azkoitia 2026",
        "ciudad": "",
        "fechaini": "26-07-2026",
        "fechafin": "26-07-2026",
        "organizador": "Anaitasuna-Kakute Xake Taldea",
        "ritmo": "Blitz, 3 minutos + 2 segundos por jugada",
        "lat": 39.3260685,
        "lon": -4.8379791,
        "link": "https://chess-results.com/tnr1387225.aspx?lan=2"
    },
    {
        "origin": "chess-results",
        "nombre": "XXXII Cto. de Ajedrez Senior por equipos Marina Al",
        "ciudad": "Casa de Cultura Jaume Pastor y Fluixa, Avda Masnou 1, 03710, Calpe, Alicante",
        "fechaini": "25-07-2026",
        "fechafin": "25-07-2026",
        "organizador": "",
        "ritmo": "5' + 3'' por jugada",
        "lat": 40.4167,
        "lon": -3.7033,
        "link": "https://chess-results.com/tnr1402659.aspx?lan=2"
    },
    {
        "origin": "chess-results",
        "nombre": "XXXII Cto. de Ajedrez Sub 16 por equipos Marina Al",
        "ciudad": "Casa de Cultura Jaume Pastor y Fluixa, Avda Masnou 1, 03710, Calpe, Alicante",
        "fechaini": "25-07-2026",
        "fechafin": "25-07-2026",
        "organizador": "",
        "ritmo": "5' + 3'' por jugada",
        "lat": 40.4167,
        "lon": -3.7033,
        "link": "https://chess-results.com/tnr1402663.aspx?lan=2"
    },
    {
        "origin": "chess-results",
        "nombre": "XIV Torneo Internacional Cidade de Pontevedra \"Ama",
        "ciudad": "Pabellón Deportivo Universitario Pontevedra – Cruz Roja s/n – 36.002 Pontevedra",
        "fechaini": "24-07-2026",
        "fechafin": "30-07-2026",
        "organizador": "(IO) Garcia Castro, Pablo (2209365)",
        "ritmo": "90 minutes with 30 second increment from move 1",
        "lat": 40.4167,
        "lon": -3.7033,
        "link": "https://chess-results.com/tnr1360195.aspx?lan=2"
    },
    {
        "origin": "chess-results",
        "nombre": "XIV Torneo Internacional Cidade de Pontevedra \"Mas",
        "ciudad": "Pabellón Deportivo Universitario Pontevedra – Cruz Roja s/n – 36.002 Pontevedra",
        "fechaini": "24-07-2026",
        "fechafin": "30-07-2026",
        "organizador": "(IO) Garcia Castro, Pablo (2209365)",
        "ritmo": "90 minutes with 30 second increment from move 1",
        "lat": 40.4167,
        "lon": -3.7033,
        "link": "https://chess-results.com/tnr1360196.aspx?lan=2"
    },
    {
        "origin": "chess-results",
        "nombre": "XIV Edición Torneo de Ajedrez de las Fiestas del C",
        "ciudad": "Torrelodones, Madrid",
        "fechaini": "19-07-2026",
        "fechafin": "19-07-2026",
        "organizador": "C.A. Torrelodones",
        "ritmo": "10 minutes + 3 seconds per movement",
        "lat": 40.5762809,
        "lon": -3.928603,
        "link": "https://chess-results.com/tnr1442195.aspx?lan=2"
    },
    {
        "origin": "chess-results",
        "nombre": "Circuito Diputación de Cádiz Sub1700 FIDE “Ciudad",
        "ciudad": "Parque Natural los Toruños, Av. del Mar, 7, 11500 El Puerto de Sta. María, Cádiz",
        "fechaini": "18-07-2026",
        "fechafin": "18-07-2026",
        "organizador": "Peña Ajedrecistica Portuense",
        "ritmo": "50 min + 10 sec por jugada",
        "lat": 40.4167,
        "lon": -3.7033,
        "link": "https://chess-results.com/tnr1441250.aspx?lan=2"
    },
    {
        "origin": "chess-results",
        "nombre": "I Open SUB10 Ciudad de El Puerto de Santa Maria 20",
        "ciudad": "Parque Natural los Toruños, Av. del Mar, 7, 11500 El Puerto de Sta. María, Cádiz",
        "fechaini": "18-07-2026",
        "fechafin": "18-07-2026",
        "organizador": "Peña Ajedrecistica Portuense",
        "ritmo": "8 min + 3 sec por jugada",
        "lat": 40.4167,
        "lon": -3.7033,
        "link": "https://chess-results.com/tnr1441254.aspx?lan=2"
    },
    {
        "origin": "chess-results",
        "nombre": "IV Open AJEDUCA Ciudad de El Puerto de Santa Maria",
        "ciudad": "Parque Natural los Toruños, Av. del Mar, 7, 11500 El Puerto de Sta. María, Cádiz",
        "fechaini": "18-07-2026",
        "fechafin": "18-07-2026",
        "organizador": "Peña Ajedrecistica Portuense",
        "ritmo": "8 min + 3 sec por jugada",
        "lat": 40.4167,
        "lon": -3.7033,
        "link": "https://chess-results.com/tnr1441253.aspx?lan=2"
    },
    {
        "origin": "chess-results",
        "nombre": "Torneo de Ajedrez Feria de Villarrubia 2026",
        "ciudad": "Centro Civico de Villarrubia",
        "fechaini": "18-07-2026",
        "fechafin": "18-07-2026",
        "organizador": "Comisión de Feria Villarrubia 2026",
        "ritmo": "10+5",
        "lat": 40.4167,
        "lon": -3.7033,
        "link": "https://chess-results.com/tnr1426278.aspx?lan=2"
    },
    {
        "origin": "chess-results",
        "nombre": "V Open de Grado - Fiesta Santiago y Santa Ana",
        "ciudad": "Grado",
        "fechaini": "18-07-2026",
        "fechafin": "18-07-2026",
        "organizador": "Peña Ajedrecista Gradense",
        "ritmo": "15'+3'' (Fischer)",
        "lat": 43.2980596,
        "lon": -6.1471901,
        "link": "https://chess-results.com/tnr1393306.aspx?lan=2"
    },
    {
        "origin": "chess-results",
        "nombre": "V TORNEO DE LA AMISTAD BERAUN BERA",
        "ciudad": "Colegio Koldo Mitxelena, Errenteria",
        "fechaini": "18-07-2026",
        "fechafin": "18-07-2026",
        "organizador": "Beraun Bera Xake Taldea",
        "ritmo": "3+2",
        "lat": 43.3140504,
        "lon": -1.8999769,
        "link": "https://chess-results.com/tnr1443293.aspx?lan=2"
    },
    {
        "origin": "chess-results",
        "nombre": "XIX   Torneo Internacional de Ajedrez de Alcubierr",
        "ciudad": "Alcubierre",
        "fechaini": "18-07-2026",
        "fechafin": "19-07-2026",
        "organizador": "Ayuntamiento de Alcubierre",
        "ritmo": "15min + 3seg/jug",
        "lat": 41.8074299,
        "lon": -0.4533294,
        "link": "https://chess-results.com/tnr1444019.aspx?lan=2"
    },
    {
        "origin": "chess-results",
        "nombre": "XXXVIII Ciudad de El Puerto de Santa Maria 2026",
        "ciudad": "Parque Natural los Toruños, Av. del Mar, 7, 11500 El Puerto de Sta. María, Cádiz",
        "fechaini": "16-07-2026",
        "fechafin": "19-07-2026",
        "organizador": "Peña Ajedrecistica Portuense",
        "ritmo": "60 min + 30 sec por jugada",
        "lat": 40.4167,
        "lon": -3.7033,
        "link": "https://chess-results.com/tnr1441247.aspx?lan=2"
    },
    {
        "origin": "chess-results",
        "nombre": "Campeonato de Canarias Absoluto y Femenino 2026",
        "ciudad": "Hotel Abora Catarina - Playa del Inglés (Gran Canaria)",
        "fechaini": "15-07-2026",
        "fechafin": "19-07-2026",
        "organizador": "Federación Canaria de Ajedrez / FIAGC",
        "ritmo": "90 min + 30 seg por movimiento",
        "lat": 40.4167,
        "lon": -3.7033,
        "link": "https://chess-results.com/tnr1439456.aspx?lan=2"
    },
    {
        "origin": "chess-results",
        "nombre": "I Open Internacional Fuxan os Ventos Lugo",
        "ciudad": "Auditorio Fuxan os Ventos - Lugo",
        "fechaini": "13-07-2026",
        "fechafin": "19-07-2026",
        "organizador": "Escola Luguesa de xadrez",
        "ritmo": "90+30",
        "lat": 42.9999682,
        "lon": -7.5577147,
        "link": "https://chess-results.com/tnr1378144.aspx?lan=2"
    },
    {
        "origin": "chess-results",
        "nombre": "VI Open Internacional CA MONTEOLIVETE",
        "ciudad": "Valencia, C/ Escultor José Capuz, 44 Bajo Izq. 46006 Valencia",
        "fechaini": "13-07-2026",
        "fechafin": "19-07-2026",
        "organizador": "CA MONTEOLIVETE",
        "ritmo": "90 min + 30 s from move 1",
        "lat": 40.4167,
        "lon": -3.7033,
        "link": "https://chess-results.com/tnr1404282.aspx?lan=2"
    },
    {
        "origin": "chess-results",
        "nombre": "IV Torneo Blitz Monumento al Campesino 2026",
        "ciudad": "Salones Museo Al Campesino. Mozaga. Lanzarote.",
        "fechaini": "12-07-2026",
        "fechafin": "12-07-2026",
        "organizador": "Club de Ajedrez El Tablero de Guanapay",
        "ritmo": "5 minutos + 3 segundos por movimiento",
        "lat": 40.4167,
        "lon": -3.7033,
        "link": "https://chess-results.com/tnr1410650.aspx?lan=2"
    },
    {
        "origin": "chess-results",
        "nombre": "III Torneo Blitz Verano Fiestas del Carmen 2026",
        "ciudad": "C/ Velarde, 1 - Las Huesas, Telde (Gran Canaria)",
        "fechaini": "11-07-2026",
        "fechafin": "11-07-2026",
        "organizador": "CA Academy",
        "ritmo": "3 Minutos + 2 segundos por movimiento",
        "lat": 40.4167,
        "lon": -3.7033,
        "link": "https://chess-results.com/tnr1439392.aspx?lan=2"
    },
    {
        "origin": "chess-results",
        "nombre": "III Torneo Blitz Verano Fiestas del Carmen 2026 Af",
        "ciudad": "C/ Velarde, 1 - Las Huesas, Telde (Gran Canaria)",
        "fechaini": "11-07-2026",
        "fechafin": "11-07-2026",
        "organizador": "CA Academy",
        "ritmo": "3 Minutos + 2 segundos por movimiento",
        "lat": 40.4167,
        "lon": -3.7033,
        "link": "https://chess-results.com/tnr1439393.aspx?lan=2"
    },
    {
        "origin": "chess-results",
        "nombre": "III Torneo de Ajedrez Villablanca Tierra de Danzas",
        "ciudad": "Villablanca (Huelva)",
        "fechaini": "11-07-2026",
        "fechafin": "11-07-2026",
        "organizador": "Escuela de Ajedrez Bambuchess",
        "ritmo": "8'+3\"",
        "lat": 37.3028005,
        "lon": -7.3423138,
        "link": "https://chess-results.com/tnr1426643.aspx?lan=2"
    },
    {
        "origin": "chess-results",
        "nombre": "XXXI Open Ciudad De Chiclana 2026",
        "ciudad": "Polideportivo Huerta Rosario, Callejon de los Frailes S/n",
        "fechaini": "11-07-2026",
        "fechafin": "11-07-2026",
        "organizador": "C.D.A. RUY LOPEZ CHICLANA",
        "ritmo": "15 MIN + 10 SEG POR JUGADA",
        "lat": 40.4167,
        "lon": -3.7033,
        "link": "https://chess-results.com/tnr1431856.aspx?lan=2"
    },
    {
        "origin": "chess-results",
        "nombre": "XXIII Open Internacional de La AntillaXI Memorial",
        "ciudad": "La Antilla (Huelva)",
        "fechaini": "10-07-2026",
        "fechafin": "10-07-2026",
        "organizador": "",
        "ritmo": "8'+3\"",
        "lat": 37.2075848,
        "lon": -7.2116537,
        "link": "https://chess-results.com/tnr1426644.aspx?lan=2"
    },
    {
        "origin": "chess-results",
        "nombre": "FESTIVAL - Curso Árbitro Autonómico FADA (Sevilla)",
        "ciudad": "HOTEL VERTICE ALJARAFE****, Avenida República Argentina s/n, Bormujos",
        "fechaini": "06-07-2026",
        "fechafin": "06-07-2026",
        "organizador": "Delegación Sevillana y Delegación Onubense de Ajedrez",
        "ritmo": "25 horas Nivel I y 40 horas Nivel II",
        "lat": 40.4167,
        "lon": -3.7033,
        "link": "https://chess-results.com/tnr1381483.aspx?lan=2"
    },
    {
        "origin": "chess-results",
        "nombre": "Torneo Internacional de Rápidas",
        "ciudad": "Calle Príncipe de Vergara 142, 28002 Madrid 2ª planta",
        "fechaini": "05-07-2026",
        "fechafin": "05-07-2026",
        "organizador": "Ajedrez Capablanca",
        "ritmo": "10+2",
        "lat": 40.4167,
        "lon": -3.7033,
        "link": "https://chess-results.com/tnr1413232.aspx?lan=2"
    },
    {
        "origin": "chess-results",
        "nombre": "XLV OPEN INTERNACIONAL \"VILLA DE BENASQUE\"",
        "ciudad": "Benasque",
        "fechaini": "05-07-2026",
        "fechafin": "14-07-2026",
        "organizador": "Ayuntamiento de Benasque - OI Delgado Crespo, Mairelys (3501868)",
        "ritmo": "90' + 30\" per move",
        "lat": 42.6052663,
        "lon": 0.5237318,
        "link": "https://chess-results.com/tnr1384253.aspx?lan=2"
    },
    {
        "origin": "chess-results",
        "nombre": "Campeonato de Menorca de Ajedrez Rapido 2026",
        "ciudad": "Es Mercadal (Menorca) - Centre de Convencions",
        "fechaini": "04-07-2026",
        "fechafin": "05-07-2026",
        "organizador": "Delegació de Menorca de la Federació Balear d'Escacs - Club Penya Alfil Mercadal",
        "ritmo": "Ràpid: 15' jugador + 5\" jugada",
        "lat": 40.4167,
        "lon": -3.7033,
        "link": "https://chess-results.com/tnr1435953.aspx?lan=2"
    },
    {
        "origin": "chess-results",
        "nombre": "Campionat de Menorca d'Escacs Ràpid Categoria Esco",
        "ciudad": "Es Mercadal (Menorca) - Centre de Convencions",
        "fechaini": "04-07-2026",
        "fechafin": "04-07-2026",
        "organizador": "Delegació de Menorca de la Federació Balear d'Escacs - Club Penya Alfil Mercadal",
        "ritmo": "Ràpid: 10' jugador + 5\" jugada",
        "lat": 40.4167,
        "lon": -3.7033,
        "link": "https://chess-results.com/tnr1441646.aspx?lan=2"
    },
    {
        "origin": "chess-results",
        "nombre": "XXXVI San Buenaventura de Moraleja(Caceres)",
        "ciudad": "Moraleja(Caceres)",
        "fechaini": "04-07-2026",
        "fechafin": "04-07-2026",
        "organizador": "Asociacion Moralejana de Ajedrez",
        "ritmo": "25'+3\"",
        "lat": 40.0684783,
        "lon": -6.6604414,
        "link": "https://chess-results.com/tnr1439246.aspx?lan=2"
    },
    {
        "origin": "chess-results",
        "nombre": "Zumárragako Xake Txapelketa 2026 Helduak  1ºJulen",
        "ciudad": "Euskadi Plazan",
        "fechaini": "04-07-2026",
        "fechafin": "04-07-2026",
        "organizador": "Carlos",
        "ritmo": "(10)+(5+5)",
        "lat": 40.4167,
        "lon": -3.7033,
        "link": "https://chess-results.com/tnr1443844.aspx?lan=2"
    },
    {
        "origin": "chess-results",
        "nombre": "Zumárragako Xake Txapelketa 2026 SUB15 1ª Julen Al",
        "ciudad": "Euskadi Plazan",
        "fechaini": "04-07-2026",
        "fechafin": "04-07-2026",
        "organizador": "",
        "ritmo": "",
        "lat": 40.4167,
        "lon": -3.7033,
        "link": "https://chess-results.com/tnr1443850.aspx?lan=2"
    },
    {
        "origin": "chess-results",
        "nombre": "III OPEN INTERNACIONAL DE AJEDREZ CIUDAD DE POZUEL",
        "ciudad": "Univ. Francisco de Vitoria, Pozuelo de Alarcon, Madrid, Spain",
        "fechaini": "03-07-2026",
        "fechafin": "12-07-2026",
        "organizador": "C.A.P.A. Club de Ajedrez Pozuelo de Alarcón",
        "ritmo": "90'+30\" each move",
        "lat": 40.4167,
        "lon": -3.7033,
        "link": "https://chess-results.com/tnr1410156.aspx?lan=2"
    },
    {
        "origin": "chess-results",
        "nombre": "Campeonato de Canarias Juvenil 2026",
        "ciudad": "Sociedad Democracia, Avda. Rafael González, 19. Arrecife (Lanzarote)",
        "fechaini": "02-07-2026",
        "fechafin": "05-07-2026",
        "organizador": "Federación Canaria de Ajedrez / Sociedad Democracia",
        "ritmo": "90 min + 30 seg por movimiento",
        "lat": 40.4167,
        "lon": -3.7033,
        "link": "https://chess-results.com/tnr1430418.aspx?lan=2"
    },
    {
        "origin": "chess-results",
        "nombre": "Campeonato de Canarias Veteranos 2026",
        "ciudad": "Sociedad Democracia, Avda. Rafael González, 19. Arrecife (Lanzarote)",
        "fechaini": "02-07-2026",
        "fechafin": "05-07-2026",
        "organizador": "Federación Canaria de Ajedrez / Sociedad Democracia",
        "ritmo": "90 min + 30 seg por movimiento",
        "lat": 40.4167,
        "lon": -3.7033,
        "link": "https://chess-results.com/tnr1430417.aspx?lan=2"
    },
    {
        "origin": "chess-results",
        "nombre": "GayGames Blitz 2026",
        "ciudad": "Centro deportivo La petxina, Valencia",
        "fechaini": "02-07-2026",
        "fechafin": "02-07-2026",
        "organizador": "C.D. Basilio",
        "ritmo": "5 min + 3seg",
        "lat": 40.4167,
        "lon": -3.7033,
        "link": "https://chess-results.com/tnr1444393.aspx?lan=2"
    },
    {
        "origin": "chess-results",
        "nombre": "III MEMORIAL JUAN MIGUEL ABRIL RODRIGUEZMAYORES",
        "ciudad": "PASEO MARÍTIMO DE ESTEPONA JUNTO A OFICINA DE CORREOS",
        "fechaini": "02-07-2026",
        "fechafin": "02-07-2026",
        "organizador": "ILMO. AYUNTAMIENTO DE ESTEPONA",
        "ritmo": "10 Minutos",
        "lat": 40.4167,
        "lon": -3.7033,
        "link": "https://chess-results.com/tnr1444150.aspx?lan=2"
    },
    {
        "origin": "chess-results",
        "nombre": "III MEMORIAL JUAN MIGUEL ABRIL RODRIGUEZSENIORS",
        "ciudad": "PASEO MARÍTIMO DE ESTEPONA JUNTO A OFICINA DE CORREOS",
        "fechaini": "02-07-2026",
        "fechafin": "02-07-2026",
        "organizador": "ILMO. AYUNTAMIENTO DE ESTEPONA",
        "ritmo": "15 Minutos",
        "lat": 40.4167,
        "lon": -3.7033,
        "link": "https://chess-results.com/tnr1444151.aspx?lan=2"
    },
    {
        "origin": "chess-results",
        "nombre": "III MEMORIAL JUAN MIGUEL ABRIL RODRIGUEZSUB08 Y PI",
        "ciudad": "PASEO MARÍTIMO DE ESTEPONA JUNTO A OFICINA DE CORREOS",
        "fechaini": "02-07-2026",
        "fechafin": "02-07-2026",
        "organizador": "ILMO. AYUNTAMIENTO DE ESTEPONA",
        "ritmo": "10 Minutos",
        "lat": 40.4167,
        "lon": -3.7033,
        "link": "https://chess-results.com/tnr1444152.aspx?lan=2"
    },
    {
        "origin": "chess-results",
        "nombre": "III MEMORIAL JUAN MIGUEL ABRIL RODRIGUEZSUB10 Y SU",
        "ciudad": "PASEO MARÍTIMO DE ESTEPONA JUNTO A OFICINA DE CORREOS",
        "fechaini": "02-07-2026",
        "fechafin": "02-07-2026",
        "organizador": "ILMO. AYUNTAMIENTO DE ESTEPONA",
        "ritmo": "10 Minutos",
        "lat": 40.4167,
        "lon": -3.7033,
        "link": "https://chess-results.com/tnr1444153.aspx?lan=2"
    },
    {
        "origin": "chess-results",
        "nombre": "III MEMORIAL JUAN MIGUEL ABRIL RODRIGUEZSUB14 Y SU",
        "ciudad": "PASEO MARÍTIMO DE ESTEPONA JUNTO A OFICINA DE CORREOS",
        "fechaini": "02-07-2026",
        "fechafin": "02-07-2026",
        "organizador": "ILMO. AYUNTAMIENTO DE ESTEPONA",
        "ritmo": "10 Minutos",
        "lat": 40.4167,
        "lon": -3.7033,
        "link": "https://chess-results.com/tnr1444154.aspx?lan=2"
    },
    {
        "origin": "chess-results",
        "nombre": "Campament Escacs 2026",
        "ciudad": "Casa de Colonias Binicanella",
        "fechaini": "01-07-2026",
        "fechafin": "04-07-2026",
        "organizador": "Associació Freestyle Chess Balears",
        "ritmo": "",
        "lat": 40.4167,
        "lon": -3.7033,
        "link": "https://chess-results.com/tnr1435140.aspx?lan=2"
    },
    {
        "origin": "chess-results",
        "nombre": "44. Azkoitia Hiria Txapelketa - 44 Torneo Villa Az",
        "ciudad": "",
        "fechaini": "28-06-2026",
        "fechafin": "28-06-2026",
        "organizador": "Anaitasuna-Kakute Xake Taldea",
        "ritmo": "Blitz, 3 minutos + 2 segundos por jugada",
        "lat": 39.3260685,
        "lon": -4.8379791,
        "link": "https://chess-results.com/tnr1362098.aspx?lan=2"
    },
    {
        "origin": "chess-results",
        "nombre": "I Freestyle Binissalem 2026",
        "ciudad": "Binissalem",
        "fechaini": "28-06-2026",
        "fechafin": "28-06-2026",
        "organizador": "Associació Freestyle Chess Balears - Club Escacs Binissalem",
        "ritmo": "5' + 3\"",
        "lat": 39.6889279,
        "lon": 2.8420532,
        "link": "https://chess-results.com/tnr1443352.aspx?lan=2"
    },
    {
        "origin": "chess-results",
        "nombre": "I TORNEO AJEDREZ SAN JUAN MAPFRE ALQUERIAS 2026",
        "ciudad": "CENTRO SOCIAL ALQUERIAS",
        "fechaini": "28-06-2026",
        "fechafin": "28-06-2026",
        "organizador": "CLUB DE AJEDREZ SAN JUAN",
        "ritmo": "7`+3´´",
        "lat": 38.7447425,
        "lon": -0.4368822,
        "link": "https://chess-results.com/tnr1429287.aspx?lan=2"
    },
    {
        "origin": "chess-results",
        "nombre": "II Campeonato de Ajedrez Hotel Vía Sevilla-Cadiz",
        "ciudad": "Hotel Vía Sevilla-Cadiz El Cuervo",
        "fechaini": "28-06-2026",
        "fechafin": "28-06-2026",
        "organizador": "Club de Ajedrez Celada",
        "ritmo": "8 minutos + 3 segundos por jugada",
        "lat": 40.4167,
        "lon": -3.7033,
        "link": "https://chess-results.com/tnr1443471.aspx?lan=2"
    },
    {
        "origin": "chess-results",
        "nombre": "Memorial Caballo Blanco Casino de Galdar 2026",
        "ciudad": "Casino de Gáldar. Plaza de Santiago,7. Gáldar",
        "fechaini": "28-06-2026",
        "fechafin": "28-06-2026",
        "organizador": "Sociedad de Fomento, Instrucción y Recreo Casino de Gáldar y FIAGC",
        "ritmo": "5 minutos + 3 segundos de incremento por jugada",
        "lat": 40.4167,
        "lon": -3.7033,
        "link": "https://chess-results.com/tnr1431123.aspx?lan=2"
    },
    {
        "origin": "chess-results",
        "nombre": "TORNEIG SOCIAL D' ESTIU 2026 COR DE MARINA",
        "ciudad": "CARRER MARINA 63",
        "fechaini": "28-06-2026",
        "fechafin": "28-06-2026",
        "organizador": "COR DE MARINA",
        "ritmo": "3+2",
        "lat": 41.3915206,
        "lon": 2.1907387,
        "link": "https://chess-results.com/tnr1443142.aspx?lan=2"
    },
    {
        "origin": "chess-results",
        "nombre": "Torneo Excalibur Junio 26",
        "ciudad": "",
        "fechaini": "28-06-2026",
        "fechafin": "28-06-2026",
        "organizador": "",
        "ritmo": "5'+3''",
        "lat": 39.3260685,
        "lon": -4.8379791,
        "link": "https://chess-results.com/tnr1413231.aspx?lan=2"
    },
    {
        "origin": "chess-results",
        "nombre": "XVII Torneig Vila de Calp 2026",
        "ciudad": "Casa Nova, Urb. Ortenbach, 11, 03710 Calp, Alicante.",
        "fechaini": "28-06-2026",
        "fechafin": "28-06-2026",
        "organizador": "Club Ajedrez Calp",
        "ritmo": "5 minutos por jugador más 3 seg. de incremento por jugada.",
        "lat": 40.4167,
        "lon": -3.7033,
        "link": "https://chess-results.com/tnr1402543.aspx?lan=2"
    },
    {
        "origin": "chess-results",
        "nombre": "Campeonato Regional de Ajedrez Relampago Por Equip",
        "ciudad": "Bodegas BSI, Jumilla",
        "fechaini": "27-06-2026",
        "fechafin": "27-06-2026",
        "organizador": "Federacion Ajedrez Region de Murcia",
        "ritmo": "3+2",
        "lat": 40.4167,
        "lon": -3.7033,
        "link": "https://chess-results.com/tnr1444066.aspx?lan=2"
    },
    {
        "origin": "chess-results",
        "nombre": "FIN DE CURSO 2026 SANTA CRUZ DE LA ZARZA/TARANCÓN",
        "ciudad": "PISCINA DE SANTA CRUZ DE LA ZARZA",
        "fechaini": "27-06-2026",
        "fechafin": "27-06-2026",
        "organizador": "SANTA CRUZ DE LA ZARZA Y CAISSAJEDREZ",
        "ritmo": "7 MIN MAS 3 S3EG",
        "lat": 40.4167,
        "lon": -3.7033,
        "link": "https://chess-results.com/tnr1443786.aspx?lan=2"
    },
    {
        "origin": "chess-results",
        "nombre": "II Lince Andujar Chess Festival 2026",
        "ciudad": "Andujar",
        "fechaini": "27-06-2026",
        "fechafin": "03-07-2026",
        "organizador": "Club de Ajedrez Andujar",
        "ritmo": "90 mintuos + 30 segundos",
        "lat": 38.0392362,
        "lon": -4.0505603,
        "link": "https://chess-results.com/tnr1364562.aspx?lan=2"
    },
    {
        "origin": "chess-results",
        "nombre": "II Open Ajedrez El Almendro Activo de Huelva",
        "ciudad": "",
        "fechaini": "27-06-2026",
        "fechafin": "27-06-2026",
        "organizador": "",
        "ritmo": "10+5",
        "lat": 39.3260685,
        "lon": -4.8379791,
        "link": "https://chess-results.com/tnr1441249.aspx?lan=2"
    },
    {
        "origin": "chess-results",
        "nombre": "II Open Internacional ACOJE Jerez",
        "ciudad": "Cadiz",
        "fechaini": "27-06-2026",
        "fechafin": "27-06-2026",
        "organizador": "Delegación Gaditana de Ajedrez",
        "ritmo": "8 min + 3 seg",
        "lat": 36.5297438,
        "lon": -6.2928976,
        "link": "https://chess-results.com/tnr1404347.aspx?lan=2"
    },
    {
        "origin": "chess-results",
        "nombre": "II Open Internacional ACOJE Jerez AJEDUCA",
        "ciudad": "Cadiz",
        "fechaini": "27-06-2026",
        "fechafin": "27-06-2026",
        "organizador": "Delegación Gaditana de Ajedrez",
        "ritmo": "8 min + 3 seg",
        "lat": 36.5297438,
        "lon": -6.2928976,
        "link": "https://chess-results.com/tnr1404349.aspx?lan=2"
    },
    {
        "origin": "chess-results",
        "nombre": "II Open Internacional ACOJE Jerez SUB1600",
        "ciudad": "Cadiz",
        "fechaini": "27-06-2026",
        "fechafin": "27-06-2026",
        "organizador": "Delegación Gaditana de Ajedrez",
        "ritmo": "8 min + 3 seg",
        "lat": 36.5297438,
        "lon": -6.2928976,
        "link": "https://chess-results.com/tnr1404348.aspx?lan=2"
    },
    {
        "origin": "chess-results",
        "nombre": "IV TORNEO DE AJEDREZ NOCTURNO ABGENA GINES (SUB-22",
        "ciudad": "Polideportivo Municipal de Gines en Calle Virgen del Pilar S/N.",
        "fechaini": "27-06-2026",
        "fechafin": "28-06-2026",
        "organizador": "Abgena Gines y Excmo. Ayuntamiento de Gines",
        "ritmo": "8 minutos + 3 segundos/jugada",
        "lat": 40.4167,
        "lon": -3.7033,
        "link": "https://chess-results.com/tnr1443306.aspx?lan=2"
    },
    {
        "origin": "chess-results",
        "nombre": "ROUND ROBIN 16 EXCALIBUR",
        "ciudad": "Restaurante EXCALIBUR.  Av/ Salvador Allende, 15. ZARAGOZA (ESPAÑA)",
        "fechaini": "27-06-2026",
        "fechafin": "27-06-2026",
        "organizador": "",
        "ritmo": "3´+2´´",
        "lat": 40.4167,
        "lon": -3.7033,
        "link": "https://chess-results.com/tnr1434557.aspx?lan=2"
    },
    {
        "origin": "chess-results",
        "nombre": "TORNEO DE AJEDREZ FIN DE CURSO JUMILLA 2026TORNEO",
        "ciudad": "Bodegas BSI. (Avda. Murcia s/n, Jumilla)",
        "fechaini": "27-06-2026",
        "fechafin": "27-06-2026",
        "organizador": "Asociación Deportiva Coímbra. Escuela de Ajedrez.",
        "ritmo": "8 minutos + 3 segundos de incremento por jugada",
        "lat": 40.4167,
        "lon": -3.7033,
        "link": "https://chess-results.com/tnr1434809.aspx?lan=2"
    },
    {
        "origin": "chess-results",
        "nombre": "TORNEO DE AJEDREZ FIN DE CURSO JUMILLA 2026TORNEO",
        "ciudad": "Bodegas BSI. (Avda. Murcia s/n, Jumilla)",
        "fechaini": "27-06-2026",
        "fechafin": "27-06-2026",
        "organizador": "Asociación Deportiva Coímbra. Escuela de Ajedrez.",
        "ritmo": "8 minutos + 3 segundos de incremento por jugada",
        "lat": 40.4167,
        "lon": -3.7033,
        "link": "https://chess-results.com/tnr1434811.aspx?lan=2"
    },
    {
        "origin": "chess-results",
        "nombre": "XXVII Open Camping Don Cactus \"Fiestas de Carchuna",
        "ciudad": "Camping Don Cactus, Carchuna",
        "fechaini": "27-06-2026",
        "fechafin": "27-06-2026",
        "organizador": "CA Motril",
        "ritmo": "8+3",
        "lat": 36.6975476,
        "lon": -3.4419311,
        "link": "https://chess-results.com/tnr1437503.aspx?lan=2"
    },
    {
        "origin": "chess-results",
        "nombre": "II TORNEO AJEDREZ MAJADAHONDA JOVEN 26 JUNIO 2026",
        "ciudad": "Centro juvenil Príncipe de Asturias de Majadahonda",
        "fechaini": "26-06-2026",
        "fechafin": "26-06-2026",
        "organizador": "Concejalia de juventud del Ayto Majadahonda y Club de ajedrez EL MOLINILLO",
        "ritmo": "10 minutos finish",
        "lat": 40.4743937,
        "lon": -3.8663563,
        "link": "https://chess-results.com/tnr1444308.aspx?lan=2"
    },
    {
        "origin": "chess-results",
        "nombre": "Social de Verano Martintxo sub 18",
        "ciudad": "Vitoria - Gasteiz, Martintxo",
        "fechaini": "25-06-2026",
        "fechafin": "25-06-2026",
        "organizador": "",
        "ritmo": "",
        "lat": 40.4167,
        "lon": -3.7033,
        "link": "https://chess-results.com/tnr1414379.aspx?lan=2"
    },
    {
        "origin": "chess-results",
        "nombre": "C.C. Xanadú Junio 2026",
        "ciudad": "Arroyomolinos (Madrid)",
        "fechaini": "24-06-2026",
        "fechafin": "24-06-2026",
        "organizador": "",
        "ritmo": "Rapid: 5min +3sec increment per move starting from move 1",
        "lat": 40.2729225,
        "lon": -3.9157978,
        "link": "https://chess-results.com/tnr1443787.aspx?lan=2"
    },
    {
        "origin": "chess-results",
        "nombre": "Social de Verano Martintxo sub 14",
        "ciudad": "Vitoria - Gasteiz, Martintxo",
        "fechaini": "24-06-2026",
        "fechafin": "24-06-2026",
        "organizador": "Martintxo",
        "ritmo": "7+3",
        "lat": 40.4167,
        "lon": -3.7033,
        "link": "https://chess-results.com/tnr1414378.aspx?lan=2"
    },
    {
        "origin": "chess-results",
        "nombre": "V BLITZ SAN JULIÁN - 7ª Etapa Circuito Urbano",
        "ciudad": "C. de Madre Dolores Márquez, 11, Casco Antiguo, 41003 Sevilla",
        "fechaini": "24-06-2026",
        "fechafin": "24-06-2026",
        "organizador": "Bar Cuatrogatos",
        "ritmo": "5 minutos + 3 segundos / jugada",
        "lat": 40.4167,
        "lon": -3.7033,
        "link": "https://chess-results.com/tnr1414816.aspx?lan=2"
    },
    {
        "origin": "chess-results",
        "nombre": "X Open Internacional RGCC 2026 - II Memorial Marco",
        "ciudad": "Hotel 1907 Villa de Gijón",
        "fechaini": "22-06-2026",
        "fechafin": "28-06-2026",
        "organizador": "Grupo Cultura Covadonga",
        "ritmo": "90'+30''(Fischer)",
        "lat": 40.4167,
        "lon": -3.7033,
        "link": "https://chess-results.com/tnr1434801.aspx?lan=2"
    },
    {
        "origin": "chess-results",
        "nombre": "PEPITO",
        "ciudad": "",
        "fechaini": "19-06-2026",
        "fechafin": "29-06-2026",
        "organizador": "",
        "ritmo": "10´",
        "lat": 39.3260685,
        "lon": -4.8379791,
        "link": "https://chess-results.com/tnr1434729.aspx?lan=2"
    },
    {
        "origin": "chess-results",
        "nombre": "prueba",
        "ciudad": "",
        "fechaini": "09-06-2026",
        "fechafin": "22-08-2026",
        "organizador": "JESUS GALVEZ",
        "ritmo": "10'+3",
        "lat": 39.3260685,
        "lon": -4.8379791,
        "link": "https://chess-results.com/tnr1434982.aspx?lan=2"
    },
    {
        "origin": "chess-results",
        "nombre": "III Social Cerrado de Ajedrez Clasico Costa Fenici",
        "ciudad": "",
        "fechaini": "27-05-2026",
        "fechafin": "08-07-2026",
        "organizador": "Club Costa Fenicia",
        "ritmo": "50 + 10",
        "lat": 39.3260685,
        "lon": -4.8379791,
        "link": "https://chess-results.com/tnr1421287.aspx?lan=2"
    },
    {
        "origin": "chess-results",
        "nombre": "XXXI OPEN SOCIAL RUY LOPEZ FUNDACION VIPREN 2026",
        "ciudad": "POLIDEPORTIVO SANTA ANA, CALLE AGUSTIN BLAZQUEZ S/N, CHICLANA DE LA FRONTERA",
        "fechaini": "24-05-2026",
        "fechafin": "28-06-2026",
        "organizador": "C.D.A. RUY LOPEZ CHICLANA",
        "ritmo": "90 MIN + 30 SEG POR JUGADA",
        "lat": 40.4167,
        "lon": -3.7033,
        "link": "https://chess-results.com/tnr1399509.aspx?lan=2"
    },
    {
        "origin": "chess-results",
        "nombre": "XXXI SUB 1600 SOCIAL RUY LOPEZ FUNDACION VIPREN",
        "ciudad": "POLIDEPORTIVO SANTA ANA, CALLE AGUSTIN BLAZQUEZ S/N, CHICLANA DE LA FRONTERA",
        "fechaini": "24-05-2026",
        "fechafin": "28-06-2026",
        "organizador": "C.D.A. RUY LOPEZ CHICLANA",
        "ritmo": "50 MIN + 10 SEG POR JUGADA",
        "lat": 40.4167,
        "lon": -3.7033,
        "link": "https://chess-results.com/tnr1399512.aspx?lan=2"
    },
    {
        "origin": "chess-results",
        "nombre": "Torneo Social AXK 2026 - Astigarraga",
        "ciudad": "Astigarraga",
        "fechaini": "23-04-2026",
        "fechafin": "17-12-2026",
        "organizador": "Astigarraga Xake Kluba",
        "ritmo": "25+10 y 3+2",
        "lat": 43.2815684,
        "lon": -1.9474769,
        "link": "https://chess-results.com/tnr1399062.aspx?lan=2"
    },
    {
        "origin": "chess-results",
        "nombre": "OPEN DE AJEDREZ “LA DIDÁCTICA-CHAMBERÍ” PRIMAVERA",
        "ciudad": "Madrid",
        "fechaini": "21-03-2026",
        "fechafin": "27-06-2026",
        "organizador": "",
        "ritmo": "Standard: 60min +30sec increment per move starting from move 1",
        "lat": 40.416782,
        "lon": -3.703507,
        "link": "https://chess-results.com/tnr1365489.aspx?lan=2"
    },
    {
        "origin": "chess-results",
        "nombre": "Torneo suizo Los Mosqueteros 25/26 (II)",
        "ciudad": "Madrid",
        "fechaini": "15-02-2026",
        "fechafin": "30-06-2026",
        "organizador": "",
        "ritmo": "Rapid: 30min +10sec increment per move starting from move 1",
        "lat": 40.416782,
        "lon": -3.703507,
        "link": "https://chess-results.com/tnr1362287.aspx?lan=2"
    },
    {
        "origin": "chess-results",
        "nombre": "Campeonato CA Villa de La Zubia 2026",
        "ciudad": "La Zubia",
        "fechaini": "01-01-2026",
        "fechafin": "31-01-2027",
        "organizador": "C. A. Villa de La Zubia",
        "ritmo": "30'+10''",
        "lat": 37.1206862,
        "lon": -3.5850833,
        "link": "https://chess-results.com/tnr1306719.aspx?lan=2"
    },
    {
        "origin": "chess-results",
        "nombre": "Lliga Club d'Escacs Calp 2026",
        "ciudad": "Calp",
        "fechaini": "01-01-2026",
        "fechafin": "31-12-2026",
        "organizador": "Club d'Escacs Calp",
        "ritmo": "5+3",
        "lat": 38.6443252,
        "lon": 0.046012,
        "link": "https://chess-results.com/tnr1327195.aspx?lan=2"
    },
    {
        "origin": "chess-results",
        "nombre": "XXI Abierto Infantil Ribera del EbroCategoría B",
        "ciudad": "Cintruénigo, Calahorra, Cervera del Río Alhama, Alfaro, Corella, Arnedo",
        "fechaini": "16-11-2025",
        "fechafin": "18-11-2026",
        "organizador": "Club Ajedrez Alfaro",
        "ritmo": "30 minutos a caída de bandera",
        "lat": 40.4167,
        "lon": -3.7033,
        "link": "https://chess-results.com/tnr1291699.aspx?lan=2"
    },
    {
        "origin": "chess-results",
        "nombre": "Jesus y Maria",
        "ciudad": "Valladolid",
        "fechaini": "03-11-2025",
        "fechafin": "03-07-2026",
        "organizador": "",
        "ritmo": "10m",
        "lat": 41.6200024,
        "lon": -4.7259906,
        "link": "https://chess-results.com/tnr1408792.aspx?lan=2"
    },
    {
        "origin": "chess-results",
        "nombre": "Quintana",
        "ciudad": "Valladolid",
        "fechaini": "03-11-2025",
        "fechafin": "03-07-2026",
        "organizador": "",
        "ritmo": "10m",
        "lat": 41.6200024,
        "lon": -4.7259906,
        "link": "https://chess-results.com/tnr1408794.aspx?lan=2"
    },
    {
        "origin": "chess-results",
        "nombre": "Quintana M",
        "ciudad": "Valladolid",
        "fechaini": "03-11-2025",
        "fechafin": "03-07-2026",
        "organizador": "",
        "ritmo": "10m",
        "lat": 41.6200024,
        "lon": -4.7259906,
        "link": "https://chess-results.com/tnr1408797.aspx?lan=2"
    },
    {
        "origin": "chess-results",
        "nombre": "San Jose V II",
        "ciudad": "Valladolid",
        "fechaini": "03-11-2025",
        "fechafin": "03-07-2026",
        "organizador": "",
        "ritmo": "10m",
        "lat": 41.6200024,
        "lon": -4.7259906,
        "link": "https://chess-results.com/tnr1408791.aspx?lan=2"
    },
    {
        "origin": "chess-results",
        "nombre": "SanJose Lunes",
        "ciudad": "Valladolid",
        "fechaini": "27-10-2025",
        "fechafin": "27-06-2026",
        "organizador": "",
        "ritmo": "10m",
        "lat": 41.6200024,
        "lon": -4.7259906,
        "link": "https://chess-results.com/tnr1408789.aspx?lan=2"
    }
]